mcp_figma/__init__.py
mcp_figma/server.py
mcp_figma-0.0.2.dist-info/METADATA
mcp_figma-0.0.2.dist-info/WHEEL
mcp_figma-0.0.2.dist-info/entry_points.txt
mcp_figma-0.0.2.dist-info/top_level.txt
mcp_figma-0.0.2.dist-info/RECORD
